{
  "metadata": {
    "extractedAt": "2025-06-06T02:37:51.868Z",
    "source": {
      "url": "https://medcloud2.nhi.gov.tw/imu/IMUE1000/IMUE0060",
      "title": "健保醫療資訊雲端查詢系統"
    },
    "dataCount": 17,
    "version": "2.0.7",
    "filename": "2025-06-06_10-37-51_張益隆.json",
    "personName": "張益隆"
  },
  "personalInfo": {
    "extractedAt": "2025-06-06T02:37:51.867Z",
    "source": "https://medcloud2.nhi.gov.tw/imu/IMUE1000/IMUE0060",
    "idNumber": "身分證號： H100***774",
    "name": "張益隆",
    "birthDate": "民 27/03/11"
  },
  "tableData": [
    {
      "項次": "1",
      "檢驗日期": "114/02/17",
      "醫令名稱": "總膽固醇 (Cholestero1, total)",
      "檢驗項目": "Cholesterol",
      "檢驗結果": "192 mg/dL",
      "單位": "mg/dL",
      "參考值": "[無][]",
      "檢驗方法": "Blood",
      "檢體採檢方法": "Blood",
      "檢驗類別": "生化學檢查",
      "來源": "敏盛綜合門診1532011154",
      "費用年月": "114/02",
      "註記": "健保;TAF;",
      "_表格編號": 2,
      "_資料行編號": 1
    },
    {
      "項次": "2",
      "檢驗日期": "114/02/17",
      "醫令名稱": "三酸甘油脂 (Triglyceride (TG))",
      "檢驗項目": "TG三酸甘油脂",
      "檢驗結果": "98 mg/dL",
      "單位": "mg/dL",
      "參考值": "[0][150]",
      "檢驗方法": "Blood",
      "檢體採檢方法": "Blood",
      "檢驗類別": "生化學檢查",
      "來源": "敏盛綜合門診1532011154",
      "費用年月": "114/02",
      "註記": "健保;TAF;",
      "_表格編號": 2,
      "_資料行編號": 2
    },
    {
      "項次": "3",
      "檢驗日期": "114/02/17",
      "醫令名稱": "醣化血紅素 (HbA1c (Hemoglobin A1c))",
      "檢驗項目": "HbA1C",
      "檢驗結果": "7.5 %",
      "單位": "%",
      "參考值": "[0][5.6]",
      "檢驗方法": "Blood HbA",
      "檢體採檢方法": "Blood HbA",
      "檢驗類別": "生化學檢查",
      "來源": "敏盛綜合門診1532011154",
      "費用年月": "114/02",
      "註記": "健保;TAF;",
      "_表格編號": 2,
      "_資料行編號": 3
    },
    {
      "項次": "4",
      "檢驗日期": "114/02/17",
      "醫令名稱": "尿酸 (Uric acid)",
      "檢驗項目": "Uric acid",
      "檢驗結果": "7.0 mg/dL",
      "單位": "mg/dL",
      "參考值": "[3.7][7.7]",
      "檢驗方法": "Blood",
      "檢體採檢方法": "Blood",
      "檢驗類別": "生化學檢查",
      "來源": "敏盛綜合門診1532011154",
      "費用年月": "114/02",
      "註記": "健保;TAF;",
      "_表格編號": 2,
      "_資料行編號": 4
    },
    {
      "項次": "5",
      "檢驗日期": "114/02/17",
      "醫令名稱": "肌酸酐、血 (Creatinine (B) CRTN)",
      "檢驗項目": "Creatinine",
      "檢驗結果": "1.26 mg/dL",
      "單位": "mg/dL",
      "參考值": "[0.72][1.25]",
      "檢驗方法": "Blood",
      "檢體採檢方法": "Blood",
      "檢驗類別": "生化學檢查",
      "來源": "敏盛綜合門診1532011154",
      "費用年月": "114/02",
      "註記": "健保;TAF;",
      "_表格編號": 2,
      "_資料行編號": 5
    },
    {
      "項次": "6",
      "檢驗日期": "114/02/17",
      "醫令名稱": "血清麩胺酸丙酮酸轉氨基脢 (S-GPT/ALT)",
      "檢驗項目": "G.P.T.",
      "檢驗結果": "9 U/L",
      "單位": "U/L",
      "參考值": "[0][45]",
      "檢驗方法": "Blood",
      "檢體採檢方法": "Blood",
      "檢驗類別": "生化學檢查",
      "來源": "敏盛綜合門診1532011154",
      "費用年月": "114/02",
      "註記": "健保;TAF;",
      "_表格編號": 2,
      "_資料行編號": 6
    },
    {
      "項次": "7",
      "檢驗日期": "114/02/17",
      "醫令名稱": "低密度脂蛋白－膽固醇 (LDL-C (Lowdensity lipoprotein cholesterol))",
      "檢驗項目": "L.D.L.－Cholestrol",
      "檢驗結果": "103 mg/dL",
      "單位": "mg/dL",
      "參考值": "[0][100]",
      "檢驗方法": "Blood",
      "檢體採檢方法": "Blood",
      "檢驗類別": "生化學檢查",
      "來源": "敏盛綜合門診1532011154",
      "費用年月": "114/02",
      "註記": "健保;TAF;",
      "_表格編號": 2,
      "_資料行編號": 7
    },
    {
      "項次": "8",
      "檢驗日期": "114/02/17",
      "醫令名稱": "甲狀腺刺激素免疫分析 (TSH(EIA/LIA))",
      "檢驗項目": "甲狀腺刺激素免疫分析 TSH",
      "檢驗結果": "1.5526 uIU/mL",
      "單位": "uIU/mL",
      "參考值": "[0.35][4.94]",
      "檢驗方法": "Blood",
      "檢體採檢方法": "Blood",
      "檢驗類別": "生化學檢查",
      "來源": "敏盛綜合門診1532011154",
      "費用年月": "114/02",
      "註記": "健保;TAF;",
      "_表格編號": 2,
      "_資料行編號": 8
    },
    {
      "項次": "9",
      "檢驗日期": "113/08/22",
      "醫令名稱": "總膽固醇 (Cholestero1, total)",
      "檢驗項目": "Cholesterol",
      "檢驗結果": "190 mg/dL",
      "單位": "mg/dL",
      "參考值": "[0][200]",
      "檢驗方法": "Blood",
      "檢體採檢方法": "Blood",
      "檢驗類別": "生化學檢查",
      "來源": "敏盛綜合門診1532011154",
      "費用年月": "113/08",
      "註記": "健保;TAF;",
      "_表格編號": 2,
      "_資料行編號": 9
    },
    {
      "項次": "10",
      "檢驗日期": "113/08/22",
      "醫令名稱": "三酸甘油脂 (Triglyceride (TG))",
      "檢驗項目": "TG三酸甘油脂",
      "檢驗結果": "82 mg/dL",
      "單位": "mg/dL",
      "參考值": "[0][150]",
      "檢驗方法": "Blood",
      "檢體採檢方法": "Blood",
      "檢驗類別": "生化學檢查",
      "來源": "敏盛綜合門診1532011154",
      "費用年月": "113/08",
      "註記": "健保;TAF;",
      "_表格編號": 2,
      "_資料行編號": 10
    },
    {
      "項次": "11",
      "檢驗日期": "113/08/22",
      "醫令名稱": "血液及體液葡萄糖-空腹 (Glucose-Ante Cibum, AC)",
      "檢驗項目": "Glucose AC",
      "檢驗結果": "114 mg/dL",
      "單位": "mg/dL",
      "參考值": "[70][100]",
      "檢驗方法": "Blood-AC",
      "檢體採檢方法": "Blood-AC",
      "檢驗類別": "生化學檢查",
      "來源": "敏盛綜合門診1532011154",
      "費用年月": "113/08",
      "註記": "健保;;",
      "_表格編號": 2,
      "_資料行編號": 11
    },
    {
      "項次": "12",
      "檢驗日期": "113/08/22",
      "醫令名稱": "醣化血紅素 (HbA1c (Hemoglobin A1c))",
      "檢驗項目": "HbA1C",
      "檢驗結果": "7.3 %",
      "單位": "%",
      "參考值": "[0][5.6]",
      "檢驗方法": "Blood HbA",
      "檢體採檢方法": "Blood HbA",
      "檢驗類別": "生化學檢查",
      "來源": "敏盛綜合門診1532011154",
      "費用年月": "113/08",
      "註記": "健保;TAF;",
      "_表格編號": 2,
      "_資料行編號": 12
    },
    {
      "項次": "13",
      "檢驗日期": "113/08/22",
      "醫令名稱": "肌酸酐、血 (Creatinine (B) CRTN)",
      "檢驗項目": "Creatinine",
      "檢驗結果": "1.45 mg/dL",
      "單位": "mg/dL",
      "參考值": "[0.72][1.25]",
      "檢驗方法": "Blood",
      "檢體採檢方法": "Blood",
      "檢驗類別": "生化學檢查",
      "來源": "敏盛綜合門診1532011154",
      "費用年月": "113/08",
      "註記": "健保;TAF;",
      "_表格編號": 2,
      "_資料行編號": 13
    },
    {
      "項次": "14",
      "檢驗日期": "113/08/22",
      "醫令名稱": "肌酐、尿 (Creatinine (U) CRTN)",
      "檢驗項目": "Creatinine (Urine)",
      "檢驗結果": "53.80 mg/dL",
      "單位": "mg/dL",
      "參考值": "[無][]",
      "檢驗方法": "Urine-random",
      "檢體採檢方法": "Urine-random",
      "檢驗類別": "生化學檢查",
      "來源": "敏盛綜合門診1532011154",
      "費用年月": "113/08",
      "註記": "健保;TAF;",
      "_表格編號": 2,
      "_資料行編號": 14
    },
    {
      "項次": "15",
      "檢驗日期": "113/08/22",
      "醫令名稱": "血清麩胺酸丙酮酸轉氨基脢 (S-GPT/ALT)",
      "檢驗項目": "G.P.T.",
      "檢驗結果": "9 U/L",
      "單位": "U/L",
      "參考值": "[0][55]",
      "檢驗方法": "Blood",
      "檢體採檢方法": "Blood",
      "檢驗類別": "生化學檢查",
      "來源": "敏盛綜合門診1532011154",
      "費用年月": "113/08",
      "註記": "健保;TAF;",
      "_表格編號": 2,
      "_資料行編號": 15
    },
    {
      "項次": "16",
      "檢驗日期": "113/08/22",
      "醫令名稱": "低密度脂蛋白－膽固醇 (LDL-C (Lowdensity lipoprotein cholesterol))",
      "檢驗項目": "L.D.L.－Cholestrol",
      "檢驗結果": "109 mg/dL",
      "單位": "mg/dL",
      "參考值": "[0][100]",
      "檢驗方法": "Blood",
      "檢體採檢方法": "Blood",
      "檢驗類別": "生化學檢查",
      "來源": "敏盛綜合門診1532011154",
      "費用年月": "113/08",
      "註記": "健保;TAF;",
      "_表格編號": 2,
      "_資料行編號": 16
    },
    {
      "項次": "17",
      "檢驗日期": "113/08/22",
      "醫令名稱": "微白蛋白 （免疫比濁法） (Microalbumin (Nephelometry))",
      "檢驗項目": "Microalbumin",
      "檢驗結果": "21.0 mg/L",
      "單位": "mg/L",
      "參考值": "[無][]",
      "檢驗方法": "Urine-random",
      "檢體採檢方法": "Urine-random",
      "檢驗類別": "免疫學檢查",
      "來源": "敏盛綜合門診1532011154",
      "費用年月": "113/08",
      "註記": "健保;TAF;",
      "_表格編號": 2,
      "_資料行編號": 17
    }
  ]
}